{
    "produtos": [
        {
            "id": 1,
            "nome": "mouse Microsoft",
            "valor": 15.90,
            "promocao": false,
            "valorPromo": 0,
            "imagem": "mouse.jpg"
        },
        {
            "id": 2,
            "nome": "Teclado Razer",
            "valor": 1500.00,
            "promocao": false,
            "valorPromo": 0,
            "imagem": "teclado.jpg"
        },
        {
            "id": 3,
            "nome": "Macbook Pro",
            "valor": 22500.30,
            "promocao": false,
            "valorPromo": 0,
            "imagem": "macbook.jpg"
        },
        {
            "id": 4,
            "nome": "Monitor Asus",
            "valor": 1399.89,
            "promocao": false,
            "valorPromo": 0,
            "imagem": "monitor.jpg"
        },
        {
            "id": 5,
            "nome": "mouse Corsair",
            "valor": 299.90,
            "promocao": false,
            "valorPromo": 0,
            "imagem": "mouse.jpg"
        },
        {
            "id": 6,
            "nome": "ssd",
            "valor": 199.90,
            "promocao": false,
            "valorPromo": 0,
            "imagem": "ssd.jpg"
        },
        {
            "id": 7,
            "nome": "Iphone 13 Pro",
            "valor": 7000.00,
            "promocao": false,
            "valorPromo": 0,
            "imagem": "celular.jpg"
        },
        {
            "id": 8,
            "nome": "fone Asus",
            "valor": 189.99,
            "promocao": false,
            "valorPromo": 0,
            "imagem": "fone.jpg"
        }
    ]
}